odoo8_addon_partner_firstname-8.0.2.2.1-py2.7-nspkg.pth
odoo8_addon_partner_firstname-8.0.2.2.1.dist-info/DESCRIPTION.rst
odoo8_addon_partner_firstname-8.0.2.2.1.dist-info/METADATA
odoo8_addon_partner_firstname-8.0.2.2.1.dist-info/RECORD
odoo8_addon_partner_firstname-8.0.2.2.1.dist-info/WHEEL
odoo8_addon_partner_firstname-8.0.2.2.1.dist-info/metadata.json
odoo8_addon_partner_firstname-8.0.2.2.1.dist-info/namespace_packages.txt
odoo8_addon_partner_firstname-8.0.2.2.1.dist-info/top_level.txt
odoo_addons/partner_firstname/README.rst
odoo_addons/partner_firstname/__init__.py
odoo_addons/partner_firstname/__openerp__.py
odoo_addons/partner_firstname/data/res_partner.yml
odoo_addons/partner_firstname/i18n/da.po
odoo_addons/partner_firstname/i18n/de.po
odoo_addons/partner_firstname/i18n/es.po
odoo_addons/partner_firstname/i18n/eu.po
odoo_addons/partner_firstname/i18n/fi.po
odoo_addons/partner_firstname/i18n/fr.po
odoo_addons/partner_firstname/i18n/it.po
odoo_addons/partner_firstname/i18n/nl.po
odoo_addons/partner_firstname/i18n/partner_firstname.pot
odoo_addons/partner_firstname/i18n/pt_BR.po
odoo_addons/partner_firstname/i18n/sl.po
odoo_addons/partner_firstname/models/__init__.py
odoo_addons/partner_firstname/models/base_config_settings.py
odoo_addons/partner_firstname/models/exceptions.py
odoo_addons/partner_firstname/models/res_partner.py
odoo_addons/partner_firstname/static/description/icon.png
odoo_addons/partner_firstname/tests/__init__.py
odoo_addons/partner_firstname/tests/base.py
odoo_addons/partner_firstname/tests/test_access_check.py
odoo_addons/partner_firstname/tests/test_create.py
odoo_addons/partner_firstname/tests/test_defaults.py
odoo_addons/partner_firstname/tests/test_delete.py
odoo_addons/partner_firstname/tests/test_empty.py
odoo_addons/partner_firstname/tests/test_name.py
odoo_addons/partner_firstname/tests/test_onchange.py
odoo_addons/partner_firstname/tests/test_order.py
odoo_addons/partner_firstname/views/base_config_view.xml
odoo_addons/partner_firstname/views/res_partner.xml
odoo_addons/partner_firstname/views/res_user.xml
