Metadata-Version: 2.0
Name: odoo8-addon-partner-firstname
Version: 8.0.2.2.1
Summary: Split first name and last name for non company partners
Home-page: https://odoo-community.org
Author: Camptocamp, Grupo ESOC Ingeniería de Servicios, ACSONE SA/NV, Odoo Community Association (OCA)
Author-email: support@odoo-community.org
License: AGPL-3
Platform: UNKNOWN
Classifier: Programming Language :: Python :: 2.7
Classifier: Framework :: Odoo
Classifier: License :: OSI Approved :: GNU Affero General Public License v3
Requires-Dist: odoo (<9.0a,>=8.0a)
